<?xml version="1.0" encoding="UTF-8"?>
<con:resource name="Swagger.json" path="/v2/swagger.json" id="27ba4b56-9e4a-4066-8bcd-d9ca80a467ce" xmlns:xsi="http://www.w3.org/2001/XMLSchema-instance" xmlns:con="http://eviware.com/soapui/config"><con:settings><con:setting id="27ba4b56-9e4a-4066-8bcd-d9ca80a467cefileName">Swagger.json</con:setting></con:settings><con:parameters/><con:method name="Swagger.json" id="db310f59-f971-4455-9be0-0430bac2a77c" method="GET"><con:settings/><con:parameters/><con:request name="Request 1" id="67baa3cf-43d7-4cf3-a5fb-aa1eb5b397e9" mediaType="application/json"><con:settings/><con:endpoint>http://petstore.swagger.io</con:endpoint><con:request/><con:credentials><con:selectedAuthProfile>No Authorization</con:selectedAuthProfile><con:authType>No Authorization</con:authType></con:credentials><con:jmsConfig JMSDeliveryMode="PERSISTENT"/><con:parameters/></con:request></con:method></con:resource>