<?xml version="1.0" encoding="UTF-8"?>
<con:restMockAction name="/v2/pet/{petId}" method="POST" resourcePath="/v2/pet/{petId}" id="691bf031-7996-4905-8679-19693de73dd8" xmlns:con="http://eviware.com/soapui/config"><con:settings><con:setting id="691bf031-7996-4905-8679-19693de73dd8fileName">%2Fv2%2Fpet%2F%7BpetId%7D-1</con:setting></con:settings><con:dispatchStyle>SEQUENCE</con:dispatchStyle><con:dispatchConfig/><con:dispatchXPath/><con:routeScript/><con:response name="Response 1" id="0b16c6c0-86c1-4b67-9d9a-567f081f3c82" httpResponseStatus="405" mediaType="application/json" dataSource=""><con:settings/><con:responseContent/></con:response><con:response name="Response 2" id="731275f8-53cb-469f-8819-fab9717edb67" httpResponseStatus="405" mediaType="application/xml" dataSource=""><con:settings/><con:responseContent/></con:response></con:restMockAction>